{
  "init_results": {
    "toxigen": {
      "black": 558.8495601415634,
      "asian": 709.1783792972565,
      "native_american": 598.956868827343,
      "muslim": 707.6942678689957,
      "latino": 648.5175710916519,
      "jewish": 582.2584273815155,
      "chinese": 708.148897767067,
      "lgbtq": 666.4798117280006,
      "mental_dis": 763.6233035326004,
      "physical_dis": 776.8847944736481,
      "mexican": 694.2438157200813,
      "women": 819.9651404619217,
      "middle_east": 699.1349931359291
    },
    "winobias": {
      "pro_male": 789.9635426998138,
      "pro_female": 776.2966442108154,
      "anti_female": 795.0179048776627,
      "anti_male": 788.0220096111298
    },
    "truthfulqa": {
      "misconceptions": 562.7725418806076,
      "conspiracies": 552.267387212709,
      "paranormal": 546.669505274573,
      "indexical_error": 718.6038603018889,
      "health": 590.9609639485677,
      "sociology": 684.59297311306,
      "economics": 636.269880229924,
      "law": 607.6421422958374,
      "confusion": 308.9165736998143
    }
  },
  "untrac_results": {
    "ccnewsv2": {
      "influence": {
        "toxigen": {
          "black": 91892.45291483402,
          "asian": 115152.07389426231,
          "native_american": 97162.5182440877,
          "muslim": 115634.382193923,
          "latino": 105003.6854776144,
          "jewish": 94210.77575230598,
          "chinese": 115468.07607781887,
          "lgbtq": 108282.05456632376,
          "mental_dis": 122988.11899077892,
          "physical_dis": 125970.16455245018,
          "mexican": 112903.38811177015,
          "women": 132824.83193290234,
          "middle_east": 113545.68002456427
        },
        "winobias": {
          "pro_male": 126701.72145485878,
          "pro_female": 127679.39525032043,
          "anti_female": 127179.42176187038,
          "anti_male": 127098.3005001545
        },
        "truthfulqa": {
          "misconceptions": 92651.50388634205,
          "conspiracies": 88927.00144757412,
          "paranormal": 88462.34984428938,
          "indexical_error": 115947.7807277663,
          "health": 96498.54363674588,
          "sociology": 110975.52271902561,
          "economics": 104792.61747627518,
          "law": 98475.31899356842,
          "confusion": 50510.699107354
        }
      },
      "steps": {
        "1": {
          "toxigen": {
            "black": 573.4822270870209,
            "asian": 719.6345410346985,
            "native_american": 602.0559689998627,
            "muslim": 706.4322481155396,
            "latino": 648.4540740996599,
            "jewish": 582.9013503789902,
            "chinese": 713.1504827737808,
            "lgbtq": 669.7071421146393,
            "mental_dis": 770.2782610654831,
            "physical_dis": 779.8661968708038,
            "mexican": 700.7110701799393,
            "women": 816.7820483446121,
            "middle_east": 700.6852458119392
          },
          "winobias": {
            "pro_male": 781.683736205101,
            "pro_female": 784.3732743263245,
            "anti_female": 799.0987077951431,
            "anti_male": 781.7383824586868
          },
          "truthfulqa": {
            "misconceptions": 570.1685210466385,
            "conspiracies": 554.6770516329034,
            "paranormal": 556.1685270560804,
            "indexical_error": 717.1568814892789,
            "health": 591.1097722710504,
            "sociology": 680.3881988525391,
            "economics": 644.0184101961097,
            "law": 614.025728225708,
            "confusion": 310.57470155724496
          }
        },
        "2000": {
          "toxigen": {
            "black": 4589.501811027527,
            "asian": 5708.212578296661,
            "native_american": 4846.102009773254,
            "muslim": 5669.387494087219,
            "latino": 5214.2515687942505,
            "jewish": 4668.20431470871,
            "chinese": 5682.139171600342,
            "lgbtq": 5315.2096157073975,
            "mental_dis": 6175.673585891724,
            "physical_dis": 6225.798069000244,
            "mexican": 5628.907568454742,
            "women": 6601.888637542725,
            "middle_east": 5575.37198972702
          },
          "winobias": {
            "pro_male": 6295.700084686279,
            "pro_female": 6280.6298360824585,
            "anti_female": 6276.618004798889,
            "anti_male": 6301.615379333496
          },
          "truthfulqa": {
            "misconceptions": 4594.75263261795,
            "conspiracies": 4427.033049827398,
            "paranormal": 4344.823611237282,
            "indexical_error": 5732.875088778409,
            "health": 4700.73849717882,
            "sociology": 5533.613699913025,
            "economics": 5218.116697557929,
            "law": 4910.530571937561,
            "confusion": 2494.6132588065793
          }
        },
        "4000": {
          "toxigen": {
            "black": 9401.619581222534,
            "asian": 11735.490114212036,
            "native_american": 9931.26682472229,
            "muslim": 11655.704048156738,
            "latino": 10782.718933105469,
            "jewish": 9650.740028381348,
            "chinese": 11720.487080574036,
            "lgbtq": 11118.550357341766,
            "mental_dis": 12706.523475646973,
            "physical_dis": 12887.785291671753,
            "mexican": 11608.756820678711,
            "women": 13756.442785263062,
            "middle_east": 11522.387872695923
          },
          "winobias": {
            "pro_male": 12892.38465499878,
            "pro_female": 13015.475713729858,
            "anti_female": 13019.7795753479,
            "anti_male": 12856.585718154907
          },
          "truthfulqa": {
            "misconceptions": 9419.498377799988,
            "conspiracies": 9030.313453851744,
            "paranormal": 9089.356193601623,
            "indexical_error": 11839.657505580357,
            "health": 9761.581254340277,
            "sociology": 11394.450799942017,
            "economics": 10592.185669775723,
            "law": 10095.591173171997,
            "confusion": 5171.293463600056
          }
        },
        "6000": {
          "toxigen": {
            "black": 14043.349187850952,
            "asian": 17291.430765151978,
            "native_american": 14734.557886123657,
            "muslim": 17206.154550552368,
            "latino": 15828.003311157227,
            "jewish": 14421.497951507568,
            "chinese": 17551.263359069824,
            "lgbtq": 16194.101874351501,
            "mental_dis": 18761.356731414795,
            "physical_dis": 18979.56766319275,
            "mexican": 17186.176792144775,
            "women": 20201.58862876892,
            "middle_east": 17284.126972198486
          },
          "winobias": {
            "pro_male": 19195.146251678467,
            "pro_female": 19331.853786468506,
            "anti_female": 19362.651859283447,
            "anti_male": 19247.721366882324
          },
          "truthfulqa": {
            "misconceptions": 13866.557041168213,
            "conspiracies": 13580.507066830183,
            "paranormal": 13450.704408157704,
            "indexical_error": 17873.24249611066,
            "health": 14544.700787760417,
            "sociology": 16724.784936904907,
            "economics": 15745.686755952382,
            "law": 14972.76999950409,
            "confusion": 7697.709474845852
          }
        },
        "8000": {
          "toxigen": {
            "black": 18476.185585021973,
            "asian": 22954.874389648438,
            "native_american": 19435.5277633667,
            "muslim": 22935.327381134033,
            "latino": 21084.83786392212,
            "jewish": 18940.107307434082,
            "chinese": 23144.326503753662,
            "lgbtq": 21644.74200630188,
            "mental_dis": 24776.48997402191,
            "physical_dis": 25262.142944335938,
            "mexican": 22753.109632492065,
            "women": 26639.85945892334,
            "middle_east": 22781.763772964478
          },
          "winobias": {
            "pro_male": 25638.029022216797,
            "pro_female": 25336.550941467285,
            "anti_female": 25619.367149353027,
            "anti_male": 25128.22137069702
          },
          "truthfulqa": {
            "misconceptions": 18380.53293800354,
            "conspiracies": 18090.204131843508,
            "paranormal": 18006.21528282461,
            "indexical_error": 23402.55967600108,
            "health": 19020.511905381944,
            "sociology": 22018.576389312744,
            "economics": 20878.94410342262,
            "law": 19707.6162815094,
            "confusion": 10074.15699884389
          }
        },
        "10000": {
          "toxigen": {
            "black": 23124.105785369873,
            "asian": 28897.022773742676,
            "native_american": 24472.85821723938,
            "muslim": 28537.947341918945,
            "latino": 26235.976947784424,
            "jewish": 23678.85418319702,
            "chinese": 29042.76686477661,
            "lgbtq": 27019.129013061523,
            "mental_dis": 30792.308742523193,
            "physical_dis": 31359.212482452393,
            "mexican": 28030.54990386963,
            "women": 33270.22338104248,
            "middle_east": 28755.11150741577
          },
          "winobias": {
            "pro_male": 31556.017305374146,
            "pro_female": 31631.285820007324,
            "anti_female": 31803.56488800049,
            "anti_male": 31896.423950195312
          },
          "truthfulqa": {
            "misconceptions": 22868.21171951294,
            "conspiracies": 22253.487047298935,
            "paranormal": 22024.219438892927,
            "indexical_error": 29121.333396746482,
            "health": 23871.80509982639,
            "sociology": 27616.355319976807,
            "economics": 25916.306979432396,
            "law": 24647.882247924805,
            "confusion": 12684.203790639014
          }
        },
        "12000": {
          "toxigen": {
            "black": 27361.609127044678,
            "asian": 33950.1499710083,
            "native_american": 29206.434894561768,
            "muslim": 34045.286880493164,
            "latino": 31385.372787475586,
            "jewish": 28366.986576080322,
            "chinese": 34446.382583618164,
            "lgbtq": 32054.84186553955,
            "mental_dis": 36910.97846221924,
            "physical_dis": 37365.34452819824,
            "mexican": 33943.28198623657,
            "women": 39967.47262573242,
            "middle_east": 34085.09126663208
          },
          "winobias": {
            "pro_male": 38284.43128204346,
            "pro_female": 38000.58045959473,
            "anti_female": 37924.645935058594,
            "anti_male": 38273.92778015137
          },
          "truthfulqa": {
            "misconceptions": 27341.711227416992,
            "conspiracies": 26885.868875666183,
            "paranormal": 26610.969870397286,
            "indexical_error": 34947.51881256764,
            "health": 28548.191896701388,
            "sociology": 33191.323181152344,
            "economics": 31165.941618835033,
            "law": 29486.73862838745,
            "confusion": 15158.161406512752
          }
        },
        "14000": {
          "toxigen": {
            "black": 31794.362476348877,
            "asian": 39892.53569030762,
            "native_american": 33674.39654922485,
            "muslim": 40107.67150878906,
            "latino": 36563.82654571533,
            "jewish": 33080.36338806152,
            "chinese": 40361.19394683838,
            "lgbtq": 37167.79207992554,
            "mental_dis": 42820.96249008179,
            "physical_dis": 43555.361251831055,
            "mexican": 39283.849559783936,
            "women": 46263.33369445801,
            "middle_east": 39441.05207443237
          },
          "winobias": {
            "pro_male": 43946.48140716553,
            "pro_female": 43914.460845947266,
            "anti_female": 44420.061210632324,
            "anti_male": 43993.42854309082
          },
          "truthfulqa": {
            "misconceptions": 32090.160800933838,
            "conspiracies": 30954.767608406008,
            "paranormal": 30563.876816860466,
            "indexical_error": 40335.06221252705,
            "health": 33030.11861979167,
            "sociology": 38361.50609588623,
            "economics": 36169.42129703444,
            "law": 34459.74335861206,
            "confusion": 17501.15784403027
          }
        },
        "16000": {
          "toxigen": {
            "black": 36526.02767944336,
            "asian": 45723.96897125244,
            "native_american": 38399.39984893799,
            "muslim": 45392.76268005371,
            "latino": 41601.58542251587,
            "jewish": 37336.22003555298,
            "chinese": 45572.690979003906,
            "lgbtq": 43001.566707611084,
            "mental_dis": 48807.834899902344,
            "physical_dis": 49913.81039428711,
            "mexican": 44646.15384674072,
            "women": 52993.55870056152,
            "middle_east": 45177.838191986084
          },
          "winobias": {
            "pro_male": 50464.76171875,
            "pro_female": 50282.06205749512,
            "anti_female": 50184.86811065674,
            "anti_male": 50631.74485015869
          },
          "truthfulqa": {
            "misconceptions": 36544.99708557129,
            "conspiracies": 35422.81083454457,
            "paranormal": 35414.52866097384,
            "indexical_error": 46292.61713676948,
            "health": 37794.25926215278,
            "sociology": 44121.839836120605,
            "economics": 41526.72811702806,
            "law": 39134.26929473877,
            "confusion": 19996.653626856783
          }
        },
        "18000": {
          "toxigen": {
            "black": 40807.42623901367,
            "asian": 51216.304832458496,
            "native_american": 43266.22218322754,
            "muslim": 51051.81507873535,
            "latino": 46962.13832092285,
            "jewish": 42309.645080566406,
            "chinese": 51179.662254333496,
            "lgbtq": 48201.315353393555,
            "mental_dis": 55163.05236816406,
            "physical_dis": 56505.33337020874,
            "mexican": 50649.1203918457,
            "women": 59291.63034820557,
            "middle_east": 50658.826232910156
          },
          "winobias": {
            "pro_male": 56590.11477661133,
            "pro_female": 56699.16352844238,
            "anti_female": 56766.96586608887,
            "anti_male": 56608.58673095703
          },
          "truthfulqa": {
            "misconceptions": 40807.46271133423,
            "conspiracies": 40175.42876392927,
            "paranormal": 39784.036534035855,
            "indexical_error": 51637.279305330085,
            "health": 42542.33086805556,
            "sociology": 49529.164207458496,
            "economics": 46355.638764880954,
            "law": 44120.93837738037,
            "confusion": 22467.195986897423
          }
        },
        "20000": {
          "toxigen": {
            "black": 45959.719467163086,
            "asian": 56932.930114746094,
            "native_american": 48493.44268035889,
            "muslim": 56824.258056640625,
            "latino": 51883.19706726074,
            "jewish": 47358.781593322754,
            "chinese": 56546.7087020874,
            "lgbtq": 53549.091453552246,
            "mental_dis": 61041.69867706299,
            "physical_dis": 62812.174156188965,
            "mexican": 56305.62298202515,
            "women": 65964.4252166748,
            "middle_east": 56740.53927612305
          },
          "winobias": {
            "pro_male": 62673.99465942383,
            "pro_female": 63287.13700866699,
            "anti_female": 63244.877365112305,
            "anti_male": 62832.75273132324
          },
          "truthfulqa": {
            "misconceptions": 45951.90099334717,
            "conspiracies": 44105.08805717054,
            "paranormal": 44128.618005087206,
            "indexical_error": 57070.25587628518,
            "health": 47364.66917534722,
            "sociology": 54782.23606109619,
            "economics": 51542.49949511055,
            "law": 48615.80880737305,
            "confusion": 24953.460670368553
          }
        },
        "22000": {
          "toxigen": {
            "black": 50311.51513671875,
            "asian": 62543.66468811035,
            "native_american": 53130.12869262695,
            "muslim": 62199.22993469238,
            "latino": 57097.357902526855,
            "jewish": 51327.12048339844,
            "chinese": 62893.27988433838,
            "lgbtq": 58580.205490112305,
            "mental_dis": 67352.47282409668,
            "physical_dis": 68039.13621520996,
            "mexican": 61054.03170013428,
            "women": 72460.91836547852,
            "middle_east": 62212.554374694824
          },
          "winobias": {
            "pro_male": 68906.44715881348,
            "pro_female": 69434.47161865234,
            "anti_female": 69797.99334716797,
            "anti_male": 70068.62467956543
          },
          "truthfulqa": {
            "misconceptions": 50032.08238220215,
            "conspiracies": 47813.733875363374,
            "paranormal": 48180.23785731589,
            "indexical_error": 63772.370146780304,
            "health": 51985.69366319444,
            "sociology": 60336.87240600586,
            "economics": 56412.1135071216,
            "law": 53786.13039398193,
            "confusion": 27628.60499141676
          }
        },
        "24000": {
          "toxigen": {
            "black": 54931.31118774414,
            "asian": 68437.9789276123,
            "native_american": 57443.45287322998,
            "muslim": 68420.1361541748,
            "latino": 62736.4801864624,
            "jewish": 55896.17081451416,
            "chinese": 68647.02554321289,
            "lgbtq": 63882.51976776123,
            "mental_dis": 73348.51583862305,
            "physical_dis": 75070.2225265503,
            "mexican": 67109.89766693115,
            "women": 79140.6404876709,
            "middle_east": 67991.4952545166
          },
          "winobias": {
            "pro_male": 75445.76512145996,
            "pro_female": 75358.2939453125,
            "anti_female": 75488.48316955566,
            "anti_male": 75324.80619812012
          },
          "truthfulqa": {
            "misconceptions": 54766.43817901611,
            "conspiracies": 53711.14378936531,
            "paranormal": 52232.48179354409,
            "indexical_error": 68628.7372750947,
            "health": 56629.14809027778,
            "sociology": 65771.07555389404,
            "economics": 61726.326065582485,
            "law": 58724.276527404785,
            "confusion": 30122.588932875562
          }
        },
        "26000": {
          "toxigen": {
            "black": 59053.20104980469,
            "asian": 74179.86209106445,
            "native_american": 62728.41840362549,
            "muslim": 73531.91281890869,
            "latino": 67514.1660079956,
            "jewish": 60334.998390197754,
            "chinese": 73820.26947784424,
            "lgbtq": 69068.63776397705,
            "mental_dis": 79623.99684143066,
            "physical_dis": 80208.4529876709,
            "mexican": 72080.97814941406,
            "women": 85049.6820602417,
            "middle_east": 72876.49290084839
          },
          "winobias": {
            "pro_male": 80897.4905090332,
            "pro_female": 81199.23764038086,
            "anti_female": 82336.17776489258,
            "anti_male": 81880.51779174805
          },
          "truthfulqa": {
            "misconceptions": 59882.10599517822,
            "conspiracies": 57314.97301962209,
            "paranormal": 57030.982558139534,
            "indexical_error": 73990.3331642316,
            "health": 61235.82387152778,
            "sociology": 71183.78312683105,
            "economics": 66567.37404336735,
            "law": 63612.47563171387,
            "confusion": 32824.580183225895
          }
        },
        "28000": {
          "toxigen": {
            "black": 63576.690994262695,
            "asian": 79440.5426940918,
            "native_american": 67509.15249633789,
            "muslim": 79147.39656829834,
            "latino": 72293.85395050049,
            "jewish": 65047.76474761963,
            "chinese": 79175.58805847168,
            "lgbtq": 74445.94906616211,
            "mental_dis": 84440.53147125244,
            "physical_dis": 86735.92802429199,
            "mexican": 78272.61686706543,
            "women": 91794.70819091797,
            "middle_east": 78134.38668823242
          },
          "winobias": {
            "pro_male": 88180.17915344238,
            "pro_female": 86225.58076477051,
            "anti_female": 87936.41021728516,
            "anti_male": 88363.91137695312
          },
          "truthfulqa": {
            "misconceptions": 63915.88771820068,
            "conspiracies": 61830.8347868217,
            "paranormal": 60430.64113977713,
            "indexical_error": 80064.51488095238,
            "health": 66017.01210069444,
            "sociology": 76174.63771057129,
            "economics": 72002.74590773809,
            "law": 68313.87713623047,
            "confusion": 34943.70862965947
          }
        },
        "30000": {
          "toxigen": {
            "black": 68239.66046142578,
            "asian": 85143.1040802002,
            "native_american": 71783.20517730713,
            "muslim": 85041.9137878418,
            "latino": 77686.48179626465,
            "jewish": 70381.4711227417,
            "chinese": 86203.39442443848,
            "lgbtq": 79742.8595199585,
            "mental_dis": 91596.03678894043,
            "physical_dis": 92562.41156768799,
            "mexican": 83866.34575653076,
            "women": 98994.05339813232,
            "middle_east": 84236.44525909424
          },
          "winobias": {
            "pro_male": 94326.33599853516,
            "pro_female": 94185.31057739258,
            "anti_female": 94723.00622558594,
            "anti_male": 94348.0705871582
          },
          "truthfulqa": {
            "misconceptions": 68838.77224731445,
            "conspiracies": 66210.0164123062,
            "paranormal": 66255.76568556202,
            "indexical_error": 86204.1139745671,
            "health": 71083.59104166667,
            "sociology": 82217.91464233398,
            "economics": 77740.83567176871,
            "law": 73271.59655761719,
            "confusion": 37324.42509809417
          }
        },
        "32000": {
          "toxigen": {
            "black": 72951.74116516113,
            "asian": 90747.10972595215,
            "native_american": 76884.87874603271,
            "muslim": 90594.48434448242,
            "latino": 83647.90969848633,
            "jewish": 74987.85202026367,
            "chinese": 91650.6175994873,
            "lgbtq": 85114.51739501953,
            "mental_dis": 98142.56478881836,
            "physical_dis": 98846.92820739746,
            "mexican": 89397.97041320801,
            "women": 104983.82916259766,
            "middle_east": 89623.12004089355
          },
          "winobias": {
            "pro_male": 101200.90292358398,
            "pro_female": 99253.40560913086,
            "anti_female": 100489.17037963867,
            "anti_male": 100256.77081298828
          },
          "truthfulqa": {
            "misconceptions": 73332.23597717285,
            "conspiracies": 70577.0230438469,
            "paranormal": 70321.60904190892,
            "indexical_error": 92231.75948660714,
            "health": 75246.97543402777,
            "sociology": 87295.27882385254,
            "economics": 82551.77545705783,
            "law": 78378.3240814209,
            "confusion": 39956.49731992713
          }
        },
        "34000": {
          "toxigen": {
            "black": 77368.46923828125,
            "asian": 96496.14641571045,
            "native_american": 81081.10298156738,
            "muslim": 95788.3745880127,
            "latino": 87223.65866851807,
            "jewish": 79246.69150543213,
            "chinese": 96642.12596130371,
            "lgbtq": 89810.31647491455,
            "mental_dis": 103747.76277160645,
            "physical_dis": 105837.90106201172,
            "mexican": 93866.11569213867,
            "women": 110700.81062316895,
            "middle_east": 95463.9061050415
          },
          "winobias": {
            "pro_male": 105601.27345275879,
            "pro_female": 104979.28889465332,
            "anti_female": 106574.75373840332,
            "anti_male": 105527.05030822754
          },
          "truthfulqa": {
            "misconceptions": 77027.22286987305,
            "conspiracies": 74567.45279190892,
            "paranormal": 74682.04754118217,
            "indexical_error": 97366.3206337933,
            "health": 79610.26903645834,
            "sociology": 92496.71746826172,
            "economics": 87033.2716305272,
            "law": 82521.00358963013,
            "confusion": 42028.0738946889
          }
        },
        "36000": {
          "toxigen": {
            "black": 81577.05960083008,
            "asian": 102010.23623657227,
            "native_american": 85961.12055206299,
            "muslim": 101587.44290161133,
            "latino": 92103.4669342041,
            "jewish": 84100.28532409668,
            "chinese": 101677.92483520508,
            "lgbtq": 95533.57974243164,
            "mental_dis": 109802.65707397461,
            "physical_dis": 111216.74253845215,
            "mexican": 99705.99931335449,
            "women": 117889.7474975586,
            "middle_east": 100268.31280517578
          },
          "winobias": {
            "pro_male": 112126.34244537354,
            "pro_female": 111851.06854248047,
            "anti_female": 113402.73275756836,
            "anti_male": 112162.791015625
          },
          "truthfulqa": {
            "misconceptions": 81523.69379425049,
            "conspiracies": 78736.05259811046,
            "paranormal": 78612.54290818798,
            "indexical_error": 101955.43979978355,
            "health": 85647.80203125,
            "sociology": 98645.44436645508,
            "economics": 92133.71133609694,
            "law": 87114.94239807129,
            "confusion": 44735.37116381727
          }
        },
        "38000": {
          "toxigen": {
            "black": 85214.46548461914,
            "asian": 106781.52612304688,
            "native_american": 90557.1259689331,
            "muslim": 107013.75621032715,
            "latino": 98170.88003540039,
            "jewish": 88077.48028564453,
            "chinese": 107436.69198608398,
            "lgbtq": 99901.02528381348,
            "mental_dis": 116362.73179626465,
            "physical_dis": 117769.41630554199,
            "mexican": 104843.59815979004,
            "women": 124958.61299133301,
            "middle_east": 106427.05825805664
          },
          "winobias": {
            "pro_male": 118714.96362304688,
            "pro_female": 118201.36962890625,
            "anti_female": 119425.57357788086,
            "anti_male": 118010.23977661133
          },
          "truthfulqa": {
            "misconceptions": 86591.35749053955,
            "conspiracies": 83292.56710271318,
            "paranormal": 83395.61082848837,
            "indexical_error": 108927.64767654221,
            "health": 88496.12453125,
            "sociology": 102646.7276763916,
            "economics": 96534.09146471089,
            "law": 91872.9264831543,
            "confusion": 47116.092760299885
          }
        },
        "40000": {
          "toxigen": {
            "black": 90792.71607971191,
            "asian": 115101.16137695312,
            "native_american": 95472.50540924072,
            "muslim": 113689.53437805176,
            "latino": 103311.15296173096,
            "jewish": 92928.48928833008,
            "chinese": 113207.32444763184,
            "lgbtq": 105561.87034606934,
            "mental_dis": 120895.44180297852,
            "physical_dis": 124032.63562011719,
            "mexican": 112158.82251739502,
            "women": 130634.85440063477,
            "middle_east": 111317.34638977051
          },
          "winobias": {
            "pro_male": 124693.36148071289,
            "pro_female": 125128.52458190918,
            "anti_female": 126097.65106201172,
            "anti_male": 126255.02230834961
          },
          "truthfulqa": {
            "misconceptions": 90388.08839416504,
            "conspiracies": 88077.45539607559,
            "paranormal": 88122.01147650194,
            "indexical_error": 114905.20840097402,
            "health": 94344.52049479166,
            "sociology": 108754.58529663086,
            "economics": 101909.15396471089,
            "law": 97564.29093933105,
            "confusion": 49431.05927690583
          }
        },
        "40920": {
          "toxigen": {
            "black": 92451.30247497559,
            "asian": 115861.25227355957,
            "native_american": 97761.47511291504,
            "muslim": 116342.07646179199,
            "latino": 105652.20304870605,
            "jewish": 94793.0341796875,
            "chinese": 116176.22497558594,
            "lgbtq": 108948.53437805176,
            "mental_dis": 123751.74229431152,
            "physical_dis": 126747.04934692383,
            "mexican": 113597.63192749023,
            "women": 133644.79707336426,
            "middle_east": 114244.8150177002
          },
          "winobias": {
            "pro_male": 127491.6849975586,
            "pro_female": 128455.69189453125,
            "anti_female": 127974.43966674805,
            "anti_male": 127886.32250976562
          },
          "truthfulqa": {
            "misconceptions": 93214.27642822266,
            "conspiracies": 89479.26883478682,
            "paranormal": 89009.01934956395,
            "indexical_error": 116666.38458806818,
            "health": 97089.50460069445,
            "sociology": 111660.11569213867,
            "economics": 105428.8873565051,
            "law": 99082.96113586426,
            "confusion": 50819.61568105381
          }
        }
      }
    }
  }
}